LICENSE
quicklab/__init__.py
quicklab/base.py
quicklab/cli/__init__.py
quicklab/cli/ops.py
quicklab/defaults.py
quicklab/dotenv.py
quicklab/errors.py
quicklab/files/gce_startup.sh
quicklab/files/gce_startup_gpu.sh
quicklab/io/__init__.py
quicklab/io/kv_files.py
quicklab/io/kv_gcs.py
quicklab/io/kv_local.py
quicklab/io/kvspec.py
quicklab/jupyter.py
quicklab/providers/cloudflare/__init__.py
quicklab/providers/cloudflare/common.py
quicklab/providers/cloudflare/dns.py
quicklab/providers/google/__init__.py
quicklab/providers/google/artifacts.py
quicklab/providers/google/common.py
quicklab/providers/google/compute.py
quicklab/providers/google/dns.py
quicklab/providers/google/log.py
quicklab/providers/google/storage.py
quicklab/providers/local/compute.py
quicklab/shortcuts.py
quicklab/types.py
quicklab/utils.py
quicklab-0.1.3.dist-info/LICENSE
quicklab-0.1.3.dist-info/METADATA
quicklab-0.1.3.dist-info/WHEEL
quicklab-0.1.3.dist-info/entry_points.txt
quicklab-0.1.3.dist-info/RECORD
